html_content_extractor/__init__.py
html_content_extractor/extractor.py
test/__init__.py
test/playground.py
html_content_extractor-0.0.3.dist-info/LICENSE
html_content_extractor-0.0.3.dist-info/METADATA
html_content_extractor-0.0.3.dist-info/WHEEL
html_content_extractor-0.0.3.dist-info/top_level.txt
html_content_extractor-0.0.3.dist-info/RECORD
