Metadata-Version: 2.1
Name: html-content-extractor
Version: 0.0.3
Summary: A Python package to extract the main content from HTML documents
Author-email: Kevin Sparks <pip@just-digital.net>
License: Apache License
Project-URL: Homepage, https://github.com/just-digital/html-content-extractor
Project-URL: Bug Tracker, https://github.com/just-digital/html-content-extractor/issues
Classifier: Development Status :: 3 - Alpha
Classifier: Programming Language :: Python :: 3
Classifier: License :: OSI Approved :: Apache Software License
Classifier: Operating System :: OS Independent
Classifier: Topic :: Text Processing :: Markup :: HTML
Requires-Python: >=3.7
License-File: LICENSE
Requires-Dist: beautifulsoup4 (>=4.12.2)
Requires-Dist: markdownify (==0.11.6)
